idea2production/__init__.py
idea2production/__version__.py
idea2production/main.py
idea2production-2017.0.1.1505069413.dist-info/DESCRIPTION.rst
idea2production-2017.0.1.1505069413.dist-info/METADATA
idea2production-2017.0.1.1505069413.dist-info/RECORD
idea2production-2017.0.1.1505069413.dist-info/WHEEL
idea2production-2017.0.1.1505069413.dist-info/metadata.json
idea2production-2017.0.1.1505069413.dist-info/top_level.txt
