Metadata-Version: 2.0
Name: idea2production
Version: 2017.0.1.1505069413
Summary: From Idea to Production on Python Projects
Home-page: https://github.com/me/myproject
Author: Harbor Research Laboratory UPM
Author-email: development@hrl-upm.es
License: MIT
Platform: UNKNOWN
Classifier: License :: OSI Approved :: MIT License
Classifier: Programming Language :: Python
Classifier: Programming Language :: Python :: 3.6
Classifier: Programming Language :: Python :: Implementation :: CPython
Classifier: Programming Language :: Python :: Implementation :: PyPy
Requires-Dist: requests
Requires-Dist: twine
